arkindex_export/__init__.py
arkindex_export/models.py
arkindex_export/queries.py
arkindex_export-0.2.1.dist-info/licenses/LICENSE
arkindex_export-0.2.1.dist-info/METADATA
arkindex_export-0.2.1.dist-info/WHEEL
arkindex_export-0.2.1.dist-info/top_level.txt
arkindex_export-0.2.1.dist-info/RECORD
