Metadata-Version: 2.4
Name: arkindex-export
Version: 0.2.1
Summary: Easily build queries for Arkindex sqlite exports
Author: Teklia
Author-email: contact@teklia.com
License-File: LICENSE
Requires-Dist: peewee==3.17.0
Dynamic: author
Dynamic: author-email
Dynamic: description
Dynamic: description-content-type
Dynamic: license-file
Dynamic: requires-dist
Dynamic: summary
